{
 "months": [
  "Дек",
  "Янв",
  "Фев",
  "Мар",
  "Апр",
  "Май",
  "Июн"
 ],
 "period_keys": [
  "2025-12",
  "2026-01",
  "2026-02",
  "2026-03",
  "2026-04",
  "2026-05",
  "2026-06"
 ],
 "provisional": [],
 "accounts": {
  "wb_acc1": {
   "lines": {
    "own_price": [
     4299130,
     3361791,
     4633255,
     4111291,
     3100304,
     3442094,
     4275613
    ],
    "sales": [
     3076463,
     2409249,
     3399336,
     3075776,
     2308768,
     2522850,
     3056572
    ],
    "returns": [
     98953,
     43553,
     71278,
     94852,
     71146,
     48743,
     66505
    ],
    "to_pay": [
     2688489,
     2133202,
     2981639,
     2512944,
     1931900,
     2123022,
     2530110
    ],
    "delivery": [
     470976,
     366553,
     551249,
     455396,
     412705,
     434429,
     518774
    ],
    "storage": [
     6806,
     6826,
     6770,
     13573,
     11936,
     13211,
     15387
    ],
    "acceptance": [
     35202,
     32610,
     44590,
     36510,
     35050,
     33290,
     32520
    ],
    "other": [
     174256,
     253757,
     188890,
     116997,
     90564,
     74429,
     79619
    ]
   },
   "commission": [
    289021,
    232494,
    346418,
    467980,
    305722,
    351085,
    459958
   ],
   "cogs": [
    1139543,
    933568,
    1267550,
    1086846,
    830891,
    1047622,
    1216539
   ],
   "net": [
    861706,
    539887,
    922590,
    803621,
    550754,
    520042,
    667270
   ],
   "margin": [
    20.0,
    16.1,
    19.9,
    19.5,
    17.8,
    15.1,
    15.6
   ],
   "orders": [
    1669,
    1286,
    1967,
    1681,
    1419,
    1423,
    1738
   ],
   "returns_cnt": [
    52,
    28,
    42,
    46,
    33,
    34,
    29
   ]
  },
  "wb_acc2": {
   "lines": {
    "own_price": [
     3926917,
     1738092,
     1912766,
     2415748,
     2337041,
     2957658,
     3929228
    ],
    "sales": [
     2786586,
     1252457,
     1389672,
     1811527,
     1743221,
     2164513,
     2806360
    ],
    "returns": [
     139959,
     39902,
     33173,
     33588,
     44953,
     65565,
     76461
    ],
    "to_pay": [
     2444161,
     1105363,
     1237823,
     1482107,
     1458599,
     1789571,
     2314847
    ],
    "delivery": [
     361485,
     169065,
     177976,
     206398,
     227514,
     355533,
     449985
    ],
    "storage": [
     1976,
     3121,
     3374,
     6373,
     5636,
     5575,
     8469
    ],
    "acceptance": [
     19855,
     7250,
     12220,
     17905,
     23485,
     24680,
     28415
    ],
    "other": [
     188564,
     207870,
     175996,
     57321,
     56503,
     51069,
     57372
    ]
   },
   "commission": [
    202466,
    107191,
    118677,
    295832,
    239670,
    309377,
    415052
   ],
   "cogs": [
    1626259,
    652429,
    599420,
    760740,
    731738,
    1111639,
    1385182
   ],
   "net": [
    246021,
    65628,
    268837,
    433371,
    413723,
    241074,
    385424
   ],
   "margin": [
    6.3,
    3.8,
    14.1,
    17.9,
    17.7,
    8.2,
    9.8
   ],
   "orders": [
    1299,
    643,
    647,
    791,
    888,
    1041,
    1323
   ],
   "returns_cnt": [
    43,
    22,
    16,
    15,
    17,
    26,
    33
   ]
  }
 }
}